modules/arbiter_interface/arbiter_interface.v
module arbiter_interface(
			clk,
			rst,
			enb,
			init,
			tester_input,
			arbiter_input
);

input wire clk;
input wire rst;
input wire enb;
input wire init;
input wire [127:0] tester_input;
output reg [1:0] arbiter_input;

//parameters
parameter [1:0] ON = 1'b1;                                                        
parameter [1:0] OFF = 1'b0; 
parameter [1:0] VCHANEL0 = 2'b00;
parameter [1:0] VCHANEL1 = 2'b01;
parameter [1:0] VCHANEL2 = 2'b10;
parameter [1:0] VCHANEL3 = 2'b11;

//Tabla de prioridades 
//memoria rw interna donde se guarda la tabla de arbitraje de los canales
//virtuales.
//variable auxiliar

reg  [127:0] vc_priority_table; 
//reg  [1:0] modified_vc_priority_table[63:0]; 
reg  [6:0] addr;


	


initial begin
	addr = 7'd0; 
	vc_priority_table[1:0] = VCHANEL3;	
	vc_priority_table[3:2] = VCHANEL2;	
	vc_priority_table[5:4] = VCHANEL3;	
	vc_priority_table[7:6] = VCHANEL0;	
	vc_priority_table[9:8] = VCHANEL2;	
	vc_priority_table[11:10] = VCHANEL1;	
	vc_priority_table[13:12] = VCHANEL0;	
	vc_priority_table[15:14] = VCHANEL1;	
	vc_priority_table[17:16] = VCHANEL3;	
	vc_priority_table[19:18] = VCHANEL2;	
	vc_priority_table[21:20] = VCHANEL3;	
	vc_priority_table[23:22] = VCHANEL0;	
	vc_priority_table[25:24] = VCHANEL2;	
	vc_priority_table[27:26] = VCHANEL1;	
	vc_priority_table[29:28] = VCHANEL0;	
	vc_priority_table[31:30] = VCHANEL3;	
	vc_priority_table[33:32] = VCHANEL2;	
	vc_priority_table[35:34] = VCHANEL3;	
	vc_priority_table[37:36] = VCHANEL0;	
	vc_priority_table[39:38] = VCHANEL2;	
	vc_priority_table[41:40] = VCHANEL1;	
	vc_priority_table[43:42] = VCHANEL0;	
	vc_priority_table[45:44] = VCHANEL1;	
	vc_priority_table[47:46] = VCHANEL3;	
	vc_priority_table[49:48] = VCHANEL2;	
	vc_priority_table[51:50] = VCHANEL3;	
	vc_priority_table[53:52] = VCHANEL0;	
	vc_priority_table[55:54] = VCHANEL2;	
	vc_priority_table[57:56] = VCHANEL1;	
	vc_priority_table[59:58] = VCHANEL0;	
	vc_priority_table[61:60] = VCHANEL1;	
	vc_priority_table[63:62] = VCHANEL3;	
	vc_priority_table[65:64] = VCHANEL2;	
	vc_priority_table[67:66] = VCHANEL3;	
	vc_priority_table[69:68] = VCHANEL0;	
	vc_priority_table[71:70] = VCHANEL2;	
	vc_priority_table[73:72] = VCHANEL1;	
	vc_priority_table[75:74] = VCHANEL0;	
	vc_priority_table[77:76] = VCHANEL1;	
	vc_priority_table[79:78] = VCHANEL3;	
	vc_priority_table[81:80] = VCHANEL2;	
	vc_priority_table[83:82] = VCHANEL3;	
	vc_priority_table[85:84] = VCHANEL0;	
	vc_priority_table[87:86] = VCHANEL2;	
	vc_priority_table[89:88] = VCHANEL1;	
	vc_priority_table[91:90] = VCHANEL0;	
	vc_priority_table[93:92] = VCHANEL1;	
	vc_priority_table[95:94] = VCHANEL3;	
	vc_priority_table[97:96] = VCHANEL2;	
	vc_priority_table[99:98] = VCHANEL3;	
	vc_priority_table[101:100] = VCHANEL0;	
	vc_priority_table[103:102] = VCHANEL2;	
	vc_priority_table[105:104] = VCHANEL1;	
	vc_priority_table[107:106] = VCHANEL0;	
	vc_priority_table[109:108] = VCHANEL1;	
	vc_priority_table[111:110] = VCHANEL3;	
	vc_priority_table[113:112] = VCHANEL2;	
	vc_priority_table[115:114] = VCHANEL3;	
	vc_priority_table[117:116] = VCHANEL0;	
	vc_priority_table[119:118] = VCHANEL2;	
	vc_priority_table[121:120] = VCHANEL1;	
	vc_priority_table[123:122] = VCHANEL0;	
	vc_priority_table[125:124] = VCHANEL3;
	vc_priority_table[127:126] = VCHANEL2;
end

always@(posedge clk)  begin
	if(rst)
	arbiter_input <= arbiter_input;
	else if(!rst&enb) begin
		case(init)	
		OFF: begin
			case(addr)
			7'd0: begin
			arbiter_input <= vc_priority_table[1:0];	
			addr <= addr + 7'd1;
			end	
			7'd1: begin
			arbiter_input <= vc_priority_table[3:2];	
			addr <= addr + 7'd1;
			end	
			7'd2: begin
			arbiter_input <= vc_priority_table[5:4];	
			addr <= addr + 7'd1;
			end	
			7'd3: begin
			arbiter_input <= vc_priority_table[7:6];	
			addr <= addr + 7'd1;
			end	
			7'd4: begin
			arbiter_input <= vc_priority_table[9:8];	
			addr <= addr + 7'd1;
			end	
			7'd5: begin
			arbiter_input <= vc_priority_table[11:10];	
			addr <= addr + 7'd1;
			end	
			7'd6: begin
			arbiter_input <= vc_priority_table[13:12];	
			addr <= addr + 7'd1;
			end	
			7'd7: begin
			arbiter_input <= vc_priority_table[15:14];	
			addr <= addr + 7'd1;
			end	
			7'd8: begin
			arbiter_input <= vc_priority_table[17:16];	
			addr <= addr + 7'd1;
			end	
			7'd9: begin
			arbiter_input <= vc_priority_table[19:18];	
			addr <= addr + 7'd1;
			end	
			7'd10: begin
			arbiter_input <= vc_priority_table[21:20];	
			addr <= addr + 7'd1;
			end	
			7'd11: begin
			arbiter_input <= vc_priority_table[23:22];	
			addr <= addr + 7'd1;
			end	
			7'd12: begin
			arbiter_input <= vc_priority_table[25:24];	
			addr <= addr + 7'd1;
			end	
			7'd13: begin
			arbiter_input <= vc_priority_table[27:26];	
			addr <= addr + 7'd1;
			end	
			7'd14: begin
			arbiter_input <= vc_priority_table[29:28];	
			addr <= addr + 7'd1;
			end	
			7'd15: begin
			arbiter_input <= vc_priority_table[31:30];	
			addr <= addr + 7'd1;
			end	
			7'd16: begin
			arbiter_input <= vc_priority_table[33:32];	
			addr <= addr + 7'd1;
			end	
			7'd17: begin
			arbiter_input <= vc_priority_table[35:34];	
			addr <= addr + 7'd1;
			end	
			7'd18: begin
			arbiter_input <= vc_priority_table[37:36];	
			addr <= addr + 7'd1;
			end	
			7'd19: begin
			arbiter_input <= vc_priority_table[39:38];	
			addr <= addr + 7'd1;
			end	
			7'd20: begin
			arbiter_input <= vc_priority_table[41:40];	
			addr <= addr + 7'd1;
			end	
			7'd21: begin
			arbiter_input <= vc_priority_table[43:42];	
			addr <= addr + 7'd1;
			end	
			7'd22: begin
			arbiter_input <= vc_priority_table[45:44];	
			addr <= addr + 7'd1;
			end	
			7'd23: begin
			arbiter_input <= vc_priority_table[47:46];	
			addr <= addr + 7'd1;
			end	
			7'd24: begin
			arbiter_input <= vc_priority_table[49:48];	
			addr <= addr + 7'd1;
			end	
			7'd25: begin
			arbiter_input <= vc_priority_table[51:50];	
			addr <= addr + 7'd1;
			end	
			7'd26: begin
			arbiter_input <= vc_priority_table[53:52];	
			addr <= addr + 7'd1;
			end	
			7'd27: begin
			arbiter_input <= vc_priority_table[55:54];	
			addr <= addr + 7'd1;
			end	
			7'd28: begin
			arbiter_input <= vc_priority_table[57:56];	
			addr <= addr + 7'd1;
			end	
			7'd29: begin
			arbiter_input <= vc_priority_table[59:58];	
			addr <= addr + 7'd1;
			end	
			7'd30: begin
			arbiter_input <= vc_priority_table[61:60];	
			addr <= addr + 7'd1;
			end	
			7'd31: begin
			arbiter_input <= vc_priority_table[63:62];	
			addr <= addr + 7'd1;
			end	
			7'd32: begin
			arbiter_input <= vc_priority_table[65:64];	
			addr <= addr + 7'd1;
			end	
			7'd33: begin
			arbiter_input <= vc_priority_table[67:66];	
			addr <= addr + 7'd1;
			end	
			7'd34: begin
			arbiter_input <= vc_priority_table[69:68];	
			addr <= addr + 7'd1;
			end	
			7'd35: begin
			arbiter_input <= vc_priority_table[71:70];	
			addr <= addr + 7'd1;
			end	
			7'd36: begin
			arbiter_input <= vc_priority_table[73:72];	
			addr <= addr + 7'd1;
			end	
			7'd37: begin
			arbiter_input <= vc_priority_table[75:74];	
			addr <= addr + 7'd1;
			end	
			7'd38: begin
			arbiter_input <= vc_priority_table[77:76];	
			addr <= addr + 7'd1;
			end	
			7'd39: begin
			arbiter_input <= vc_priority_table[79:78];	
			addr <= addr + 7'd1;
			end	
			7'd40: begin
			arbiter_input <= vc_priority_table[81:80];	
			addr <= addr + 7'd1;
			end
			7'd41: begin
			arbiter_input <= vc_priority_table[83:82];	
			addr <= addr + 7'd1;
			end	
			7'd42: begin
			arbiter_input <= vc_priority_table[85:84];	
			addr <= addr + 7'd1;
			end	
			7'd43: begin
			arbiter_input <= vc_priority_table[87:86];	
			addr <= addr + 7'd1;
			end	
			7'd44: begin
			arbiter_input <= vc_priority_table[89:88];	
			addr <= addr + 7'd1;
			end	
			7'd45: begin
			arbiter_input <= vc_priority_table[91:90];	
			addr <= addr + 7'd1;
			end	
			7'd46: begin
			arbiter_input <= vc_priority_table[93:92];	
			addr <= addr + 7'd1;
			end	
			7'd47: begin
			arbiter_input <= vc_priority_table[95:94];	
			addr <= addr + 7'd1;
			end	
			7'd48: begin
			arbiter_input <= vc_priority_table[97:96];	
			addr <= addr + 7'd1;
			end	
			7'd49: begin
			arbiter_input <= vc_priority_table[99:98];	
			addr <= addr + 7'd1;
			end	
			7'd50: begin
			arbiter_input <= vc_priority_table[101:100];	
			addr <= addr + 7'd1;
			end	
			7'd51: begin
			arbiter_input <= vc_priority_table[103:102];	
			addr <= addr + 7'd1;
			end	
			7'd52: begin
			arbiter_input <= vc_priority_table[105:104];	
			addr <= addr + 7'd1;
			end	
			7'd53: begin
			arbiter_input <= vc_priority_table[107:106];	
			addr <= addr + 7'd1;
			end	
			7'd54: begin
			arbiter_input <= vc_priority_table[109:108];	
			addr <= addr + 7'd1;
			end	
			7'd55: begin
			arbiter_input <= vc_priority_table[111:110];	
			addr <= addr + 7'd1;
			end	
			7'd56: begin
			arbiter_input <= vc_priority_table[113:112];	
			addr <= addr + 7'd1;
			end	
			7'd57: begin
			arbiter_input <= vc_priority_table[115:114];	
			addr <= addr + 7'd1;
			end	
			7'd58: begin
			arbiter_input <= vc_priority_table[117:116];	
			addr <= addr + 7'd1;
			end	
			7'd59: begin
			arbiter_input <= vc_priority_table[119:118];	
			addr <= addr + 7'd1;
			end	
			7'd60: begin
			arbiter_input <= vc_priority_table[121:120];	
			addr <= addr + 7'd1;
			end	
			7'd61: begin
			arbiter_input <= vc_priority_table[123:122];	
			addr <= addr + 7'd1;
			end	
			7'd62: begin
			arbiter_input <= vc_priority_table[125:124];
			addr <= addr + 7'd1;
			end	
			7'd63: begin
			arbiter_input <= vc_priority_table[127:126];
			addr <=  7'd0;
			end
			endcase	
		end
		ON: begin
			vc_priority_table[1:0] <= tester_input[1:0];  
			vc_priority_table[3:2] <= tester_input[3:2];  
			vc_priority_table[5:4] <= tester_input[5:4];  
			vc_priority_table[7:6] <= tester_input[7:6]; 
			vc_priority_table[9:8] <= tester_input[9:8]; 
			vc_priority_table[11:10] <= tester_input[11:10]; 
			vc_priority_table[13:12] <= tester_input[13:12]; 
			vc_priority_table[15:14] <= tester_input[15:14]; 
			vc_priority_table[17:16] <= tester_input[17:16]; 
			vc_priority_table[19:18] <= tester_input[19:18]; 
			vc_priority_table[21:20] <= tester_input[21:20];
			vc_priority_table[23:22] <= tester_input[23:22];
			vc_priority_table[25:24] <= tester_input[25:24];
			vc_priority_table[27:26] <= tester_input[27:26];
			vc_priority_table[29:28] <= tester_input[29:28];
			vc_priority_table[31:30] <= tester_input[31:30];
			vc_priority_table[33:32] <= tester_input[33:32];
			vc_priority_table[35:34] <= tester_input[35:34];
			vc_priority_table[37:36] <= tester_input[37:36];
			vc_priority_table[39:38] <= tester_input[39:38];
			vc_priority_table[41:40] <= tester_input[41:40];
			vc_priority_table[43:42] <= tester_input[43:42];
			vc_priority_table[45:44] <= tester_input[45:44];
			vc_priority_table[47:46] <= tester_input[47:46];
			vc_priority_table[49:48] <= tester_input[49:48];
			vc_priority_table[51:50] <= tester_input[51:50];
			vc_priority_table[53:52] <= tester_input[53:52];
			vc_priority_table[55:54] <= tester_input[55:54];
			vc_priority_table[57:56] <= tester_input[57:56];
			vc_priority_table[59:58] <= tester_input[59:58];
			vc_priority_table[61:60] <= tester_input[61:60];
			vc_priority_table[63:62] <= tester_input[63:62];
			vc_priority_table[65:64] <= tester_input[65:64];
			vc_priority_table[67:66] <= tester_input[67:66];
			vc_priority_table[69:68] <= tester_input[69:68];
			vc_priority_table[71:70] <= tester_input[71:70];
			vc_priority_table[73:72] <= tester_input[73:72];
			vc_priority_table[75:74] <= tester_input[75:74];
			vc_priority_table[77:76] <= tester_input[77:76];
			vc_priority_table[79:78] <= tester_input[79:78];
			vc_priority_table[81:80] <= tester_input[81:80];
			vc_priority_table[83:82] <= tester_input[83:82];
			vc_priority_table[85:84] <= tester_input[85:84];
			vc_priority_table[87:86] <= tester_input[87:86];
			vc_priority_table[89:88] <= tester_input[89:88];
			vc_priority_table[91:90] <= tester_input[91:90];
			vc_priority_table[93:92] <= tester_input[93:92];
			vc_priority_table[95:94] <= tester_input[95:94];
			vc_priority_table[97:96] <= tester_input[97:96];
			vc_priority_table[99:98] <= tester_input[99:98];
			vc_priority_table[101:100] <= tester_input[101:100];
			vc_priority_table[103:102] <= tester_input[103:102];
			vc_priority_table[105:104] <= tester_input[105:104];
			vc_priority_table[107:106] <= tester_input[107:106];
			vc_priority_table[109:108] <= tester_input[109:108];
			vc_priority_table[111:110] <= tester_input[111:110];
			vc_priority_table[113:112] <= tester_input[113:112];
			vc_priority_table[115:114] <= tester_input[115:114];
			vc_priority_table[117:116] <= tester_input[117:116];
			vc_priority_table[119:118] <= tester_input[119:118];
			vc_priority_table[121:120] <= tester_input[121:120];
			vc_priority_table[123:122] <= tester_input[123:122];
			vc_priority_table[125:124] <= tester_input[125:124];
			vc_priority_table[127:126] <= tester_input[127:126];
			addr <= 7'd0;                              
		end
		endcase
	end
end
endmodule

pruebas/arbiter_interface/arbiter_interface_sintetizado_tb.v
`timescale 1ns/1ps
`include "libs/cmos_cells.v"
`include "sintesis/arbiter_interface_sintetizado.v"

module arbiter_interface_tester(
			clk,
			rst,
			enb,
			init,
			tester_input,
			arbiter_input
);

output reg clk;
output reg rst;
output reg enb;
output reg init;
output reg [127:0] tester_input;
input wire [1:0] arbiter_input;

parameter [1:0] VCHANEL0 = 2'b00;
parameter [1:0] VCHANEL1 = 2'b01;
parameter [1:0] VCHANEL2 = 2'b10;
parameter [1:0] VCHANEL3 = 2'b11;
initial begin
	$dumpfile("gtkws/arbiter_interface_sintetizado.vcd");
	$dumpvars;

	clk <= 0;
	enb <= 0;
	rst <= 1;
	init <= 0;
	
	tester_input[1:0] <= VCHANEL2;	
	tester_input[3:2] <= VCHANEL0;	
	tester_input[5:4] <= VCHANEL1;	
	tester_input[7:6] <= VCHANEL2;	
	tester_input[9:8] <= VCHANEL1;	
	tester_input[11:10] <= VCHANEL2;	
	tester_input[13:12] <= VCHANEL3;	
	tester_input[15:14] <= VCHANEL2;	
	tester_input[17:16] <= VCHANEL0;	
	tester_input[19:18] <= VCHANEL1;	
	tester_input[21:20] <= VCHANEL2;	
	tester_input[23:22] <= VCHANEL3;	
	tester_input[25:24] <= VCHANEL1;	
	tester_input[27:26] <= VCHANEL2;	
	tester_input[29:28] <= VCHANEL3;	
	tester_input[31:30] <= VCHANEL1;	
	tester_input[33:32] <= VCHANEL3;	
	tester_input[35:34] <= VCHANEL2;	
	tester_input[37:36] <= VCHANEL3;	
	tester_input[39:38] <= VCHANEL0;	
	tester_input[41:40] <= VCHANEL3;	
	tester_input[43:42] <= VCHANEL1;	
	tester_input[45:44] <= VCHANEL0;	
	tester_input[47:46] <= VCHANEL2;	
	tester_input[49:48] <= VCHANEL0;	
	tester_input[51:50] <= VCHANEL1;	
	tester_input[53:52] <= VCHANEL2;	
	tester_input[55:54] <= VCHANEL1;	
	tester_input[57:56] <= VCHANEL0;	
	tester_input[59:58] <= VCHANEL2;	
	tester_input[61:60] <= VCHANEL0;	
	tester_input[63:62] <= VCHANEL2;	
	tester_input[65:64] <= VCHANEL3;	
	tester_input[67:66] <= VCHANEL1;	
	tester_input[69:68] <= VCHANEL2;	
	tester_input[71:70] <= VCHANEL1;	
	tester_input[73:72] <= VCHANEL3;	
	tester_input[75:74] <= VCHANEL2;	
	tester_input[77:76] <= VCHANEL0;	
	tester_input[79:78] <= VCHANEL2;	
	tester_input[81:80] <= VCHANEL3;	
	tester_input[83:82] <= VCHANEL1;	
	tester_input[85:84] <= VCHANEL2;	
	tester_input[87:86] <= VCHANEL1;	
	tester_input[89:88] <= VCHANEL0;	
	tester_input[91:90] <= VCHANEL2;	
	tester_input[93:92] <= VCHANEL3;	
	tester_input[95:94] <= VCHANEL0;	
	tester_input[97:96] <= VCHANEL2;	
	tester_input[99:98] <= VCHANEL0;	
	tester_input[101:100] <= VCHANEL3;	
	tester_input[103:102] <= VCHANEL0;	
	tester_input[105:104] <= VCHANEL1;	
	tester_input[107:106] <= VCHANEL2;	
	tester_input[109:108] <= VCHANEL3;	
	tester_input[111:110] <= VCHANEL1;	
	tester_input[113:112] <= VCHANEL3;	
	tester_input[115:114] <= VCHANEL2;	
	tester_input[117:116] <= VCHANEL0;	
	tester_input[119:118] <= VCHANEL2;	
	tester_input[121:120] <= VCHANEL1;	
	tester_input[123:122] <= VCHANEL3;	
	tester_input[125:124] <= VCHANEL2;
	tester_input[127:126] <= VCHANEL1;
        	
	@(posedge clk) begin
		enb <= 1;
		rst <= 0;
	end
	#135
	@(posedge clk) 
		init <= 1;

	@(posedge clk)
	#2 
		init <= 0;
	#131
	$finish;
end

always #1 clk <= ~clk;

endmodule


module arbiter_interface_tb;
 
wire clk_bus;
wire rst;
wire enb;
wire init;
wire [127:0] tester_input;
wire [1:0] arbiter_input_bus;

arbiter_interface arbiter_interface(
		.clk(clk_bus),
                .rst(rst),
                .enb(enb),
                .init(init),
		.tester_input(tester_input),
		.arbiter_input(arbiter_input_bus)
);
arbiter_interface_tester arbiter_interface_tester(
		.clk(clk_bus),
                .rst(rst),
                .enb(enb),
                .init(init),
		.tester_input(tester_input),
		.arbiter_input(arbiter_input_bus)
);



endmodule

gtkws/arbiter_interface.vcd
$date
	Sat Jun 30 21:18:47 2018
$end
$version
	Icarus Verilog
$end
$timescale
	1ps
$end
$scope module arbiter_interface_tb $end
$var wire 128 ! tester_input [127:0] $end
$var wire 1 " rst $end
$var wire 1 # init $end
$var wire 1 $ enb $end
$var wire 1 % clk_bus $end
$var wire 2 & arbiter_input_bus [1:0] $end
$scope module arbiter_interface $end
$var wire 128 ' tester_input [127:0] $end
$var wire 1 " rst $end
$var wire 1 # init $end
$var wire 1 $ enb $end
$var wire 1 % clk $end
$var reg 7 ( addr [6:0] $end
$var reg 2 ) arbiter_input [1:0] $end
$var reg 128 * vc_priority_table [127:0] $end
$upscope $end
$scope module arbiter_interface_tester $end
$var wire 2 + arbiter_input [1:0] $end
$var reg 1 % clk $end
$var reg 1 $ enb $end
$var reg 1 # init $end
$var reg 1 " rst $end
$var reg 128 , tester_input [127:0] $end
$upscope $end
$upscope $end
$enddefinitions $end
#0
$dumpvars
b1101101100010110111100100110010001110000110011110001011011001111000100001100100100001110011101101111001111001001011100110010010 ,
bx +
b10110001100011101101000110001110110100011000111011010001100011101101000110001110110100011000111011000110001110110100011000111011 *
bx )
b0 (
b1101101100010110111100100110010001110000110011110001011011001111000100001100100100001110011101101111001111001001011100110010010 '
bx &
0%
0$
0#
1"
b1101101100010110111100100110010001110000110011110001011011001111000100001100100100001110011101101111001111001001011100110010010 !
$end
#1000
0"
1$
1%
#2000
0%
#3000
b1 (
b11 &
b11 )
b11 +
1%
#4000
0%
#5000
b10 (
b10 &
b10 )
b10 +
1%
#6000
0%
#7000
b11 (
b11 &
b11 )
b11 +
1%
#8000
0%
#9000
b100 (
b0 &
b0 )
b0 +
1%
#10000
0%
#11000
b101 (
b10 &
b10 )
b10 +
1%
#12000
0%
#13000
b110 (
b1 &
b1 )
b1 +
1%
#14000
0%
#15000
b111 (
b0 &
b0 )
b0 +
1%
#16000
0%
#17000
b1000 (
b1 &
b1 )
b1 +
1%
#18000
0%
#19000
b1001 (
b11 &
b11 )
b11 +
1%
#20000
0%
#21000
b1010 (
b10 &
b10 )
b10 +
1%
#22000
0%
#23000
b1011 (
b11 &
b11 )
b11 +
1%
#24000
0%
#25000
b1100 (
b0 &
b0 )
b0 +
1%
#26000
0%
#27000
b1101 (
b10 &
b10 )
b10 +
1%
#28000
0%
#29000
b1110 (
b1 &
b1 )
b1 +
1%
#30000
0%
#31000
b1111 (
b0 &
b0 )
b0 +
1%
#32000
0%
#33000
b10000 (
b11 &
b11 )
b11 +
1%
#34000
0%
#35000
b10001 (
b10 &
b10 )
b10 +
1%
#36000
0%
#37000
b10010 (
b11 &
b11 )
b11 +
1%
#38000
0%
#39000
b10011 (
b0 &
b0 )
b0 +
1%
#40000
0%
#41000
b10100 (
b10 &
b10 )
b10 +
1%
#42000
0%
#43000
b10101 (
b1 &
b1 )
b1 +
1%
#44000
0%
#45000
b10110 (
b0 &
b0 )
b0 +
1%
#46000
0%
#47000
b10111 (
b1 &
b1 )
b1 +
1%
#48000
0%
#49000
b11000 (
b11 &
b11 )
b11 +
1%
#50000
0%
#51000
b11001 (
b10 &
b10 )
b10 +
1%
#52000
0%
#53000
b11010 (
b11 &
b11 )
b11 +
1%
#54000
0%
#55000
b11011 (
b0 &
b0 )
b0 +
1%
#56000
0%
#57000
b11100 (
b10 &
b10 )
b10 +
1%
#58000
0%
#59000
b11101 (
b1 &
b1 )
b1 +
1%
#60000
0%
#61000
b11110 (
b0 &
b0 )
b0 +
1%
#62000
0%
#63000
b11111 (
b1 &
b1 )
b1 +
1%
#64000
0%
#65000
b100000 (
b11 &
b11 )
b11 +
1%
#66000
0%
#67000
b100001 (
b10 &
b10 )
b10 +
1%
#68000
0%
#69000
b100010 (
b11 &
b11 )
b11 +
1%
#70000
0%
#71000
b100011 (
b0 &
b0 )
b0 +
1%
#72000
0%
#73000
b100100 (
b10 &
b10 )
b10 +
1%
#74000
0%
#75000
b100101 (
b1 &
b1 )
b1 +
1%
#76000
0%
#77000
b100110 (
b0 &
b0 )
b0 +
1%
#78000
0%
#79000
b100111 (
b1 &
b1 )
b1 +
1%
#80000
0%
#81000
b101000 (
b11 &
b11 )
b11 +
1%
#82000
0%
#83000
b101001 (
b10 &
b10 )
b10 +
1%
#84000
0%
#85000
b101010 (
b11 &
b11 )
b11 +
1%
#86000
0%
#87000
b101011 (
b0 &
b0 )
b0 +
1%
#88000
0%
#89000
b101100 (
b10 &
b10 )
b10 +
1%
#90000
0%
#91000
b101101 (
b1 &
b1 )
b1 +
1%
#92000
0%
#93000
b101110 (
b0 &
b0 )
b0 +
1%
#94000
0%
#95000
b101111 (
b1 &
b1 )
b1 +
1%
#96000
0%
#97000
b110000 (
b11 &
b11 )
b11 +
1%
#98000
0%
#99000
b110001 (
b10 &
b10 )
b10 +
1%
#100000
0%
#101000
b110010 (
b11 &
b11 )
b11 +
1%
#102000
0%
#103000
b110011 (
b0 &
b0 )
b0 +
1%
#104000
0%
#105000
b110100 (
b10 &
b10 )
b10 +
1%
#106000
0%
#107000
b110101 (
b1 &
b1 )
b1 +
1%
#108000
0%
#109000
b110110 (
b0 &
b0 )
b0 +
1%
#110000
0%
#111000
b110111 (
b1 &
b1 )
b1 +
1%
#112000
0%
#113000
b111000 (
b11 &
b11 )
b11 +
1%
#114000
0%
#115000
b111001 (
b10 &
b10 )
b10 +
1%
#116000
0%
#117000
b111010 (
b11 &
b11 )
b11 +
1%
#118000
0%
#119000
b111011 (
b0 &
b0 )
b0 +
1%
#120000
0%
#121000
b111100 (
b10 &
b10 )
b10 +
1%
#122000
0%
#123000
b111101 (
b1 &
b1 )
b1 +
1%
#124000
0%
#125000
b111110 (
b0 &
b0 )
b0 +
1%
#126000
0%
#127000
b111111 (
b11 &
b11 )
b11 +
1%
#128000
0%
#129000
b0 (
b10 &
b10 )
b10 +
1%
#130000
0%
#131000
b1 (
b11 &
b11 )
b11 +
1%
#132000
0%
#133000
b10 (
b10 &
b10 )
b10 +
1%
#134000
0%
#135000
b11 (
b11 &
b11 )
b11 +
1%
#136000
0%
#137000
b100 (
b0 &
b0 )
b0 +
1#
1%
#138000
0%
#139000
b0 (
b1101101100010110111100100110010001110000110011110001011011001111000100001100100100001110011101101111001111001001011100110010010 *
1%
#140000
0%
#141000
b1 (
b10 &
b10 )
b10 +
1%
0#
#142000
0%
#143000
b10 (
b0 &
b0 )
b0 +
1%
#144000
0%
#145000
b11 (
b1 &
b1 )
b1 +
1%
#146000
0%
#147000
b100 (
b10 &
b10 )
b10 +
1%
#148000
0%
#149000
b101 (
b1 &
b1 )
b1 +
1%
#150000
0%
#151000
b110 (
b10 &
b10 )
b10 +
1%
#152000
0%
#153000
b111 (
b11 &
b11 )
b11 +
1%
#154000
0%
#155000
b1000 (
b10 &
b10 )
b10 +
1%
#156000
0%
#157000
b1001 (
b0 &
b0 )
b0 +
1%
#158000
0%
#159000
b1010 (
b1 &
b1 )
b1 +
1%
#160000
0%
#161000
b1011 (
b10 &
b10 )
b10 +
1%
#162000
0%
#163000
b1100 (
b11 &
b11 )
b11 +
1%
#164000
0%
#165000
b1101 (
b1 &
b1 )
b1 +
1%
#166000
0%
#167000
b1110 (
b10 &
b10 )
b10 +
1%
#168000
0%
#169000
b1111 (
b11 &
b11 )
b11 +
1%
#170000
0%
#171000
b10000 (
b1 &
b1 )
b1 +
1%
#172000
0%
#173000
b10001 (
b11 &
b11 )
b11 +
1%
#174000
0%
#175000
b10010 (
b10 &
b10 )
b10 +
1%
#176000
0%
#177000
b10011 (
b11 &
b11 )
b11 +
1%
#178000
0%
#179000
b10100 (
b0 &
b0 )
b0 +
1%
#180000
0%
#181000
b10101 (
b11 &
b11 )
b11 +
1%
#182000
0%
#183000
b10110 (
b1 &
b1 )
b1 +
1%
#184000
0%
#185000
b10111 (
b0 &
b0 )
b0 +
1%
#186000
0%
#187000
b11000 (
b10 &
b10 )
b10 +
1%
#188000
0%
#189000
b11001 (
b0 &
b0 )
b0 +
1%
#190000
0%
#191000
b11010 (
b1 &
b1 )
b1 +
1%
#192000
0%
#193000
b11011 (
b10 &
b10 )
b10 +
1%
#194000
0%
#195000
b11100 (
b1 &
b1 )
b1 +
1%
#196000
0%
#197000
b11101 (
b0 &
b0 )
b0 +
1%
#198000
0%
#199000
b11110 (
b10 &
b10 )
b10 +
1%
#200000
0%
#201000
b11111 (
b0 &
b0 )
b0 +
1%
#202000
0%
#203000
b100000 (
b10 &
b10 )
b10 +
1%
#204000
0%
#205000
b100001 (
b11 &
b11 )
b11 +
1%
#206000
0%
#207000
b100010 (
b1 &
b1 )
b1 +
1%
#208000
0%
#209000
b100011 (
b10 &
b10 )
b10 +
1%
#210000
0%
#211000
b100100 (
b1 &
b1 )
b1 +
1%
#212000
0%
#213000
b100101 (
b11 &
b11 )
b11 +
1%
#214000
0%
#215000
b100110 (
b10 &
b10 )
b10 +
1%
#216000
0%
#217000
b100111 (
b0 &
b0 )
b0 +
1%
#218000
0%
#219000
b101000 (
b10 &
b10 )
b10 +
1%
#220000
0%
#221000
b101001 (
b11 &
b11 )
b11 +
1%
#222000
0%
#223000
b101010 (
b1 &
b1 )
b1 +
1%
#224000
0%
#225000
b101011 (
b10 &
b10 )
b10 +
1%
#226000
0%
#227000
b101100 (
b1 &
b1 )
b1 +
1%
#228000
0%
#229000
b101101 (
b0 &
b0 )
b0 +
1%
#230000
0%
#231000
b101110 (
b10 &
b10 )
b10 +
1%
#232000
0%
#233000
b101111 (
b11 &
b11 )
b11 +
1%
#234000
0%
#235000
b110000 (
b0 &
b0 )
b0 +
1%
#236000
0%
#237000
b110001 (
b10 &
b10 )
b10 +
1%
#238000
0%
#239000
b110010 (
b0 &
b0 )
b0 +
1%
#240000
0%
#241000
b110011 (
b11 &
b11 )
b11 +
1%
#242000
0%
#243000
b110100 (
b0 &
b0 )
b0 +
1%
#244000
0%
#245000
b110101 (
b1 &
b1 )
b1 +
1%
#246000
0%
#247000
b110110 (
b10 &
b10 )
b10 +
1%
#248000
0%
#249000
b110111 (
b11 &
b11 )
b11 +
1%
#250000
0%
#251000
b111000 (
b1 &
b1 )
b1 +
1%
#252000
0%
#253000
b111001 (
b11 &
b11 )
b11 +
1%
#254000
0%
#255000
b111010 (
b10 &
b10 )
b10 +
1%
#256000
0%
#257000
b111011 (
b0 &
b0 )
b0 +
1%
#258000
0%
#259000
b111100 (
b10 &
b10 )
b10 +
1%
#260000
0%
#261000
b111101 (
b1 &
b1 )
b1 +
1%
#262000
0%
#263000
b111110 (
b11 &
b11 )
b11 +
1%
#264000
0%
#265000
b111111 (
b10 &
b10 )
b10 +
1%
#266000
0%
#267000
b0 (
b1 &
b1 )
b1 +
1%
#268000
0%
#269000
b1 (
b10 &
b10 )
b10 +
1%
#270000
0%
#271000
b10 (
b0 &
b0 )
b0 +
1%
