modules/memoria/memoria.v
`timescale 1ns / 1ps
module memoria(
         input clk,                      //-- Señal de reloj global
         input wire [2: 0] AddrA,     //-- Direcciones
         input wire [2: 0] AddrB,     //-- Direcciones
         input wire rwA,                 //-- Modo lectura (1) o escritura (0)
         input wire rwB,                 //-- Modo lectura (1) o escritura (0)
         input wire [3: 0] DataInA,   //-- Dato de entrada
         input wire [3: 0] DataInB,   //-- Dato de entrada
         output reg [3: 0] DataOutA,  //-- Dato a escribir
         output reg [3: 0] DataOutB); //-- Dato a escribir

//-- Calcular el numero de posiciones totales de memoria
localparam NPOS = 2 ** 3;

  //-- Declaracion de memoria RAM
  reg [4-1: 0] ram [0: NPOS-1];

  // Port A
	always @ (posedge clk)
	begin
		if (rwA)
		begin
			ram[AddrA] <= DataInA;
		end
		else
		begin
			DataOutA <= ram[AddrA];
		end
	end

	// Port B
	always @ (posedge clk)
	begin
		if (rwB)
		begin
			ram[AddrB] <= DataInB; 
		end
		else
		begin
			DataOutB <= ram[AddrB];
		end
	end

endmodule

modules/memoria/testSintetizado.v
`timescale 1ns / 1ps
module tester#(             //-- Parametros
         parameter AW = 3,   //-- Bits de las direcciones (Adress width)
         parameter DW = 4)   //-- Bits de los datos (Data witdh)

       (        //-- Puertos
             output reg clk,                      //-- Señal de reloj global
             output reg [AW-1: 0] AddrA,      //-- Direcciones
             output reg [AW-1: 0] AddrB,
             output reg rwA,                  //-- Modo lectura (1) o escritura (0)
             output reg rwB,                  //-- Modo lectura (1) o escritura (0)
             output reg [DW-1: 0] DataInA,   //-- Dato de entrada
             output reg [DW-1: 0] DataInB);   //-- Dato de entrada


          //Se setea el clock
always
  begin
    #4 clk <= ~clk;
  end

           //Valores iniciales
initial begin
             clk=0;
             rwA<=0;
             rwB<=0;



          // Prueba 1 Data A in
          rwA<=1;
          AddrA<=2'b10;
          #8
          DataInA<=4'b1001;
          #32

          // Prueba 2 Data out A
          rwA<=0;
          AddrA<=2'b10;
          #32

          // Prueba 3 Data out A
          rwA<=0;
          AddrA<=2'b00;
          #32

       	  // Prueba 4 Data B in
          rwB<=1;
          AddrB<=2'b11;
          #8
       	  DataInB<=4'b1010;
          #32

          // Prueba 5 Data out B
          rwB<=0;
          AddrB<=2'b10;
          #32

          // Prueba 6 Data out B
          rwB<=0;
          AddrB<=2'b11;
          #32




$finish;
end
endmodule

modules/memoria/memoriaTB.v
`timescale 1ns / 1ps
module memoriaTB();

wire [2: 0] AddrA;
wire [2: 0] AddrB;
wire [3: 0] DataInA;
wire [3: 0] DataInB;
output wire [3: 0] DataOutA;
output wire [3: 0] DataOutB;
wire rwA;
wire rwB;


  tester t_1(clk, AddrA, AddrB,rwA, rwB, DataInA, DataInB);
  memoria m_1 (clk, AddrA, AddrB, rwA, rwB, DataInA, DataInB, DataOutA, DataOutB);

  initial
    begin
      $dumpfile("Verificador.vcd");
      $dumpvars;
    end

endmodule

gtkws/memoriaConductual.vcd
$date
	Sat Jun 30 19:49:45 2018
$end
$version
	Icarus Verilog
$end
$timescale
	1ps
$end
$scope module memoriaTB $end
$var wire 1 ! rwB $end
$var wire 1 " rwA $end
$var wire 1 # clk $end
$var wire 4 $ DataOutB [3:0] $end
$var wire 4 % DataOutA [3:0] $end
$var wire 4 & DataInB [3:0] $end
$var wire 4 ' DataInA [3:0] $end
$var wire 3 ( AddrB [2:0] $end
$var wire 3 ) AddrA [2:0] $end
$scope module m_1 $end
$var wire 1 ! rwB $end
$var wire 1 " rwA $end
$var wire 1 # clk $end
$var wire 4 * DataInB [3:0] $end
$var wire 4 + DataInA [3:0] $end
$var wire 3 , AddrB [2:0] $end
$var wire 3 - AddrA [2:0] $end
$var reg 4 . DataOutA [3:0] $end
$var reg 4 / DataOutB [3:0] $end
$upscope $end
$scope module t_1 $end
$var reg 3 0 AddrA [2:0] $end
$var reg 3 1 AddrB [2:0] $end
$var reg 4 2 DataInA [3:0] $end
$var reg 4 3 DataInB [3:0] $end
$var reg 1 # clk $end
$var reg 1 " rwA $end
$var reg 1 ! rwB $end
$upscope $end
$upscope $end
$enddefinitions $end
#0
$dumpvars
bx 3
bx 2
bx 1
b10 0
bx /
bx .
b10 -
bx ,
bx +
bx *
b10 )
bx (
bx '
bx &
bx %
bx $
0#
1"
0!
$end
#4000
1#
#8000
0#
b1001 '
b1001 +
b1001 2
#12000
1#
#16000
0#
#20000
1#
#24000
0#
#28000
1#
#32000
0#
#36000
1#
#40000
0#
0"
#44000
b1001 %
b1001 .
1#
#48000
0#
#52000
1#
#56000
0#
#60000
1#
#64000
0#
#68000
1#
#72000
0#
b0 )
b0 -
b0 0
#76000
bx %
bx .
1#
#80000
0#
#84000
1#
#88000
0#
#92000
1#
#96000
0#
#100000
1#
#104000
0#
b11 (
b11 ,
b11 1
1!
#108000
1#
#112000
0#
b1010 &
b1010 *
b1010 3
#116000
1#
#120000
0#
#124000
1#
#128000
0#
#132000
1#
#136000
0#
#140000
1#
#144000
0#
b10 (
b10 ,
b10 1
0!
#148000
b1001 $
b1001 /
1#
#152000
0#
#156000
1#
#160000
0#
#164000
1#
#168000
0#
#172000
1#
#176000
0#
b11 (
b11 ,
b11 1
#180000
b1010 $
b1010 /
1#
